odoo/addons/shopinvader_promotion_rule/README.rst
odoo/addons/shopinvader_promotion_rule/__init__.py
odoo/addons/shopinvader_promotion_rule/__manifest__.py
odoo/addons/shopinvader_promotion_rule/data/cart_step.xml
odoo/addons/shopinvader_promotion_rule/i18n/shopinvader_promotion_rule.pot
odoo/addons/shopinvader_promotion_rule/models/__init__.py
odoo/addons/shopinvader_promotion_rule/models/sale_order.py
odoo/addons/shopinvader_promotion_rule/services/__init__.py
odoo/addons/shopinvader_promotion_rule/services/abstract_sale_service.py
odoo/addons/shopinvader_promotion_rule/services/cart.py
odoo/addons/shopinvader_promotion_rule/tests/__init__.py
odoo/addons/shopinvader_promotion_rule/tests/test_cart.py
odoo14_addon_shopinvader_promotion_rule-14.0.1.0.1.dist-info/METADATA
odoo14_addon_shopinvader_promotion_rule-14.0.1.0.1.dist-info/WHEEL
odoo14_addon_shopinvader_promotion_rule-14.0.1.0.1.dist-info/top_level.txt
odoo14_addon_shopinvader_promotion_rule-14.0.1.0.1.dist-info/RECORD
