Metadata-Version: 2.1
Name: odoo14-addon-shopinvader-promotion-rule
Version: 14.0.1.0.1
Summary: Module to manage Promotion Rule with shopinvader
Home-page: https://github.com/shopinvader/odoo-shopinvader
Author: Akretion, ACSONE SA / NV
License: AGPL-3
Platform: UNKNOWN
Classifier: Programming Language :: Python
Classifier: Framework :: Odoo
Classifier: Framework :: Odoo :: 14.0
Classifier: License :: OSI Approved :: GNU Affero General Public License v3
Requires-Python: >=3.6
Requires-Dist: odoo14-addon-component
Requires-Dist: odoo14-addon-sale-promotion-rule
Requires-Dist: odoo14-addon-shopinvader
Requires-Dist: odoo (<14.1dev,>=14.0a)
